{
    "name": "Global Information",
    "numberOfRequests": {
        "total": 79,
        "ok": 79,
        "ko": 0
    },
    "minResponseTime": {
        "total": 42,
        "ok": 42,
        "ko": 0
    },
    "maxResponseTime": {
        "total": 439,
        "ok": 439,
        "ko": 0
    },
    "meanResponseTime": {
        "total": 73,
        "ok": 73,
        "ko": 0
    },
    "standardDeviation": {
        "total": 50,
        "ok": 50,
        "ko": 0
    },
    "percentiles1": {
        "total": 60,
        "ok": 60,
        "ko": 0
    },
    "percentiles2": {
        "total": 79,
        "ok": 79,
        "ko": 0
    },
    "percentiles3": {
        "total": 113,
        "ok": 113,
        "ko": 0
    },
    "percentiles4": {
        "total": 250,
        "ok": 250,
        "ko": 0
    },
    "group1": {
    "name": "t < 800 ms",
    "count": 79,
    "percentage": 100
},
    "group2": {
    "name": "800 ms < t < 1200 ms",
    "count": 0,
    "percentage": 0
},
    "group3": {
    "name": "t > 1200 ms",
    "count": 0,
    "percentage": 0
},
    "group4": {
    "name": "failed",
    "count": 0,
    "percentage": 0
},
    "meanNumberOfRequestsPerSecond": {
        "total": 39.5,
        "ok": 39.5,
        "ko": 0
    }
}